st_query_input/__init__.py
st_query_input/frontend/index.html
st_query_input/frontend/main.js
st_query_input/frontend/streamlit-component-lib.js
st_query_input/frontend/style.css
streamlit_query_input-0.1.9.dist-info/LICENSE
streamlit_query_input-0.1.9.dist-info/METADATA
streamlit_query_input-0.1.9.dist-info/WHEEL
streamlit_query_input-0.1.9.dist-info/top_level.txt
streamlit_query_input-0.1.9.dist-info/RECORD
