Metadata-Version: 2.1
Name: streamlit-query-input
Version: 0.1.9
Summary: multiline text input with resut and submit buttons
Author: Justin Zhang
Author-email: justin@gmail.com
Requires-Python: >=3.7
License-File: LICENSE
Requires-Dist: streamlit >=1.2
Requires-Dist: jinja2
